log_throttling/__init__.py
log_throttling/log_throttling.py
log_throttling-0.0.2.dist-info/LICENSE
log_throttling-0.0.2.dist-info/METADATA
log_throttling-0.0.2.dist-info/WHEEL
log_throttling-0.0.2.dist-info/top_level.txt
log_throttling-0.0.2.dist-info/RECORD
