Metadata-Version: 2.1
Name: log-throttling
Version: 0.0.2
Summary: A python log throttling utility
Home-page: https://github.com/MPalarya/log-throttling
Author: Redis Inc.
Author-email: oss@redis.com
License: UNKNOWN
Project-URL: Bug Tracker, https://github.com/MPalarya/log-throttling/issues
Platform: UNKNOWN
Classifier: Programming Language :: Python :: 3
Classifier: License :: OSI Approved :: MIT License
Classifier: Operating System :: OS Independent
Requires-Python: >=3.9
License-File: LICENSE
